pactverify/__init__.py
pactverify/core.py
pactverify/matchers.py
pactverify/utils.py
tests/__init__.py
interfacepact-0.1.dist-info/METADATA
interfacepact-0.1.dist-info/WHEEL
interfacepact-0.1.dist-info/top_level.txt
interfacepact-0.1.dist-info/RECORD
